pyhk-0.1.0.dist-info/RECORD
pyhk-0.1.0.dist-info/WHEEL
pyhk-0.1.0.dist-info/METADATA
pyhk-0.1.0.dist-info/licenses/LICENCE
pyhk/_pyhk.py
pyhk/__init__.py
pyhk/rf_lib.cpython-312-darwin.so
